{
  "applications": "*",
  "changelogDate": "20220401014450",
  "dto": "mapstruct",
  "embedded": false,
  "entityTableName": "auction",
  "fields": [
    {
      "fieldName": "point",
      "fieldType": "Integer"
    },
    {
      "fieldName": "createdDate",
      "fieldType": "ZonedDateTime"
    }
  ],
  "fluentMethods": true,
  "jpaMetamodelFiltering": false,
  "name": "Auction",
  "pagination": "pagination",
  "readOnly": false,
  "relationships": [
    {
      "otherEntityName": "product",
      "otherEntityRelationshipName": "auction",
      "relationshipName": "product",
      "relationshipType": "many-to-one"
    },
    {
      "otherEntityName": "profile",
      "otherEntityRelationshipName": "auction",
      "relationshipName": "profile",
      "relationshipType": "many-to-one"
    }
  ],
  "service": "serviceImpl"
}
